{
  "version": "7",
  "dialect": "mysql",
  "entries": [
    {
      "idx": 0,
      "version": "5",
      "when": 1761296627834,
      "tag": "0000_big_galactus",
      "breakpoints": true
    },
    {
      "idx": 1,
      "version": "5",
      "when": 1761296672604,
      "tag": "0001_great_thundra",
      "breakpoints": true
    },
    {
      "idx": 2,
      "version": "5",
      "when": 1761299560023,
      "tag": "0002_windy_whistler",
      "breakpoints": true
    },
    {
      "idx": 3,
      "version": "5",
      "when": 1761299855216,
      "tag": "0003_wonderful_patch",
      "breakpoints": true
    },
    {
      "idx": 4,
      "version": "5",
      "when": 1761302848790,
      "tag": "0004_old_the_renegades",
      "breakpoints": true
    },
    {
      "idx": 5,
      "version": "5",
      "when": 1761304222450,
      "tag": "0005_right_harpoon",
      "breakpoints": true
    }
  ]
}